api_jongler/__init__.py
api_jongler/__main__.py
api_jongler/api_connector.py
api_jongler/api_jongler.py
api_jongler/cli.py
api_jongler/colored_formatter.py
api_jongler/connectors/api-inference.huggingface.co.json
api_jongler/connectors/generativelanguage.googleapis.com.json
api_jongler/connectors/httpbin.org.json
api_jongler-2.0.7.dist-info/licenses/LICENSE
tests/__init__.py
tests/test_api_jongler.py
api_jongler-2.0.7.dist-info/METADATA
api_jongler-2.0.7.dist-info/WHEEL
api_jongler-2.0.7.dist-info/entry_points.txt
api_jongler-2.0.7.dist-info/top_level.txt
api_jongler-2.0.7.dist-info/RECORD
